json_normalize/__init__.py
json_normalize/key_joiners.py
json_normalize/main.py
json_normalize-1.1.0.dist-info/LICENSE
json_normalize-1.1.0.dist-info/METADATA
json_normalize-1.1.0.dist-info/WHEEL
json_normalize-1.1.0.dist-info/top_level.txt
json_normalize-1.1.0.dist-info/RECORD
