Metadata-Version: 2.1
Name: json-normalize
Version: 1.1.0
Summary: Recursively flattens a JSON-like structure into a list of flat dicts.
Home-page: https://github.com/funnel-io/json-normalize
Author: The Funnel Dev Team
Author-email: open-source@funnel.io
License: MIT
Project-URL: Bug Reports, https://github.com/funnel-io/json-normalize/issues
Project-URL: Source, https://github.com/funnel-io/json-normalize
Keywords: JSON
Classifier: Development Status :: 5 - Production/Stable
Classifier: License :: OSI Approved :: MIT License
Classifier: Programming Language :: Python :: 3
Classifier: Programming Language :: Python :: 3.8
Classifier: Programming Language :: Python :: 3.9
Classifier: Programming Language :: Python :: 3.10
Classifier: Programming Language :: Python :: 3.11
Classifier: Programming Language :: Python :: 3.12
Classifier: Topic :: Software Development :: Libraries
License-File: LICENSE
